easyops/__init__.py
easyops/client.py
easyops/common.py
easyops/exceptions.py
easyops/apps/__init__.py
easyops/apps/_base.py
easyops/apps/appconfig.py
easyops/apps/artifact.py
easyops/apps/cmdb.py
easyops/apps/easy_flow.py
easyops/apps/easy_plugin.py
easyops/apps/scheduler.py
easyops/apps/tool.py
easyops/helper/__init__.py
easyops/helper/_apps.py
easyops/helper/_helper.py
easyops/helper/types.py
easyops/openapi/__init__.py
easyops/openapi/openapi.py
easyops/org_client/__init__.py
easyops/org_client/org.py
easyops/utils/__init__.py
easyops/utils/ns.py
easyops-1.0.12.dist-info/LICENSE
easyops-1.0.12.dist-info/METADATA
easyops-1.0.12.dist-info/WHEEL
easyops-1.0.12.dist-info/top_level.txt
easyops-1.0.12.dist-info/RECORD
